tdmelodic/__init__.py
tdmelodic/nn/__init__.py
tdmelodic/nn/convert_dic.py
tdmelodic/nn/inference.py
tdmelodic/nn/net.py
tdmelodic/nn/lang/__init__.py
tdmelodic/nn/lang/category/__init__.py
tdmelodic/nn/lang/category/symbol_map.py
tdmelodic/nn/lang/category/list_of_symbols/__init__.py
tdmelodic/nn/lang/category/list_of_symbols/acc_concat.py
tdmelodic/nn/lang/category/list_of_symbols/goshu.py
tdmelodic/nn/lang/category/list_of_symbols/pos_short.py
tdmelodic/nn/lang/japanese/__init__.py
tdmelodic/nn/lang/japanese/kansuji.py
tdmelodic/nn/lang/japanese/text_normalize.py
tdmelodic/nn/lang/japanese/accent/__init__.py
tdmelodic/nn/lang/japanese/accent/accent_alignment.py
tdmelodic/nn/lang/japanese/accent/accent_diff.py
tdmelodic/nn/lang/japanese/kana/__init__.py
tdmelodic/nn/lang/japanese/kana/hyphen2romaji.py
tdmelodic/nn/lang/japanese/kana/kana2roman.py
tdmelodic/nn/lang/japanese/kana/mora_sep.py
tdmelodic/nn/lang/japanese/kana/kanamap/__init__.py
tdmelodic/nn/lang/japanese/kana/kanamap/kanamap_normal.py
tdmelodic/nn/lang/mecab/__init__.py
tdmelodic/nn/lang/mecab/my_mecabrc
tdmelodic/nn/lang/mecab/unidic.py
tdmelodic/nn/loader/__init__.py
tdmelodic/nn/loader/data_loader.py
tdmelodic/nn/loader/data_loader_base.py
tdmelodic/nn/model/__init__.py
tdmelodic/nn/model/decode_accent.py
tdmelodic/nn/model/encode_morae.py
tdmelodic/nn/model/encode_surface.py
tdmelodic/nn/model/modules/__init__.py
tdmelodic/nn/model/modules/cnn_attention.py
tdmelodic/nn/model/modules/dilateconvcausal1d.py
tdmelodic/nn/model/modules/gatedconv1d.py
tdmelodic/nn/model/modules/stacked_conv.py
tdmelodic/nn/resource/net_it_2500000
tdmelodic/script/__init__.py
tdmelodic/script/neologd_patch.py
tdmelodic/script/postprocess_modify_unigram_cost.py
tdmelodic-1.0.0.dist-info/LICENSE
tdmelodic-1.0.0.dist-info/METADATA
tdmelodic-1.0.0.dist-info/WHEEL
tdmelodic-1.0.0.dist-info/entry_points.txt
tdmelodic-1.0.0.dist-info/top_level.txt
tdmelodic-1.0.0.dist-info/RECORD
