Metadata-Version: 2.1
Name: tdmelodic
Version: 1.0.0
Summary: tdmelodic: Tokyo Japanese Accent Estimator
Home-page: https://github.com/PKSHATechnology-Research/tdmelodic
Author: Hideyuki Tachibana
Author-email: h_tachibana@pkshatech.com
License: UNKNOWN
Platform: UNKNOWN
Classifier: Development Status :: 5 - Production/Stable
Classifier: Environment :: Console
Classifier: Intended Audience :: Science/Research
Classifier: Intended Audience :: Developers
Classifier: License :: OSI Approved :: BSD License
Classifier: Operating System :: POSIX
Classifier: Programming Language :: Python :: 3.7
Classifier: Topic :: Text Processing :: Linguistic
Classifier: Topic :: Multimedia :: Sound/Audio :: Speech
Classifier: Topic :: Scientific/Engineering :: Artificial Intelligence
Classifier: Natural Language :: Japanese
Requires-Python: >=3.7
Requires-Dist: numpy (>=1.15.4)
Requires-Dist: chainer (>=5.1.0)
Requires-Dist: mecab-python3 (>=0.996.1)
Requires-Dist: jaconv (>=0.2.4)
Requires-Dist: python-Levenshtein (>=0.12.0)
Requires-Dist: tqdm (>=4.42.1)
Requires-Dist: regex (>=2020.1.8)
Requires-Dist: matplotlib (>=3.0.0)
